rctSlime/__init__.py
rctSlime/network.py
rctSlime/ppo.py
rctSlime-0.0.2.dist-info/METADATA
rctSlime-0.0.2.dist-info/WHEEL
rctSlime-0.0.2.dist-info/top_level.txt
rctSlime-0.0.2.dist-info/RECORD
